{"trial_id": "18", "hyperparameters": {"space": [{"class_name": "Choice", "config": {"name": "batch_size", "default": 16, "conditions": [], "values": [8, 16, 32, 64], "ordered": true}}, {"class_name": "Float", "config": {"name": "lr", "default": 1e-05, "conditions": [], "min_value": 1e-05, "max_value": 0.01, "step": 2, "sampling": "log"}}, {"class_name": "Float", "config": {"name": "momentum", "default": 0.5, "conditions": [], "min_value": 0.5, "max_value": 1.0, "step": 0.05, "sampling": "linear"}}], "values": {"batch_size": 64, "lr": 0.00064, "momentum": 0.95}}, "metrics": {"metrics": {"accuracy": {"direction": "max", "observations": [{"value": [0.9012150168418884], "step": 12}]}, "iter_0_1_loss": {"direction": "min", "observations": [{"value": [6.233333110809326], "step": 12}]}, "loss": {"direction": "min", "observations": [{"value": [0.2519718408584595], "step": 12}]}, "total_0-1_loss": {"direction": "min", "observations": [{"value": [374.0], "step": 12}]}, "val_accuracy": {"direction": "max", "observations": [{"value": [0.8458289504051208], "step": 12}]}, "val_iter_0_1_loss": {"direction": "min", "observations": [{"value": [4.866666793823242], "step": 12}]}, "val_loss": {"direction": "min", "observations": [{"value": [0.3485316336154938], "step": 12}]}, "val_total_0-1_loss": {"direction": "min", "observations": [{"value": [146.0], "step": 12}]}}}, "score": 0.3485316336154938, "best_step": 12, "status": "COMPLETED", "message": null}