{"trial_id": "08", "hyperparameters": {"space": [{"class_name": "Choice", "config": {"name": "batch_size", "default": 16, "conditions": [], "values": [8, 16, 32, 64], "ordered": true}}, {"class_name": "Float", "config": {"name": "lr", "default": 1e-05, "conditions": [], "min_value": 1e-05, "max_value": 0.001, "step": 2, "sampling": "log"}}, {"class_name": "Float", "config": {"name": "momentum", "default": 0.5, "conditions": [], "min_value": 0.5, "max_value": 1.0, "step": 0.05, "sampling": "linear"}}], "values": {"batch_size": 64, "lr": 0.00016, "momentum": 0.65}}, "metrics": {"metrics": {"accuracy": {"direction": "max", "observations": [{"value": [0.7707343101501465], "step": 12}]}, "iter_0_1_loss": {"direction": "min", "observations": [{"value": [14.466666221618652], "step": 12}]}, "loss": {"direction": "min", "observations": [{"value": [0.48652997612953186], "step": 12}]}, "total_0-1_loss": {"direction": "min", "observations": [{"value": [868.0], "step": 12}]}, "val_accuracy": {"direction": "max", "observations": [{"value": [0.76346355676651], "step": 12}]}, "val_iter_0_1_loss": {"direction": "min", "observations": [{"value": [7.4666666984558105], "step": 12}]}, "val_loss": {"direction": "min", "observations": [{"value": [0.5076210498809814], "step": 12}]}, "val_total_0-1_loss": {"direction": "min", "observations": [{"value": [224.0], "step": 12}]}}}, "score": 0.5076210498809814, "best_step": 12, "status": "COMPLETED", "message": null}